README.md
setup.py
lightningdata/__init__.py
lightningdata/common/__init__.py
lightningdata/common/config.py
lightningdata/common/folder2lmdb.py
lightningdata/common/pre_process.py
lightningdata/common/utils.py
lightningdata/modules/__init__.py
lightningdata/modules/datamodule_base.py
lightningdata/modules/domain_adaptation/__init__.py
lightningdata/modules/domain_adaptation/digit5_datamodule.py
lightningdata/modules/domain_adaptation/domainAdaptation_base.py
lightningdata/modules/domain_adaptation/domainNet_datamodule.py
lightningdata/modules/domain_adaptation/office31_datamodule.py
lightningdata/modules/domain_adaptation/officeHome_datamodule.py
lightningdata/modules/federated_learning/__init__.py
lightningdata/modules/federated_learning/emnist_datamodule.py
lightningdata/modules/federated_learning/federatedLearning_base.py
lightningdata/modules/meta_learning/__init__.py
lightningdata/modules/meta_learning/metaLearning_base.py
lightningdata/modules/meta_learning/mini_imagenet_datamodule.py
lightningdata/modules/meta_learning/omiglot_datamodule.py
lightningdata/thirdparty/__init__.py
lightningdata/thirdparty/torchmeta/__init__.py
lightningdata/thirdparty/torchmeta/version.py
lightningdata/thirdparty/torchmeta/datasets/__init__.py
lightningdata/thirdparty/torchmeta/datasets/bach.py
lightningdata/thirdparty/torchmeta/datasets/cub.py
lightningdata/thirdparty/torchmeta/datasets/doublemnist.py
lightningdata/thirdparty/torchmeta/datasets/helpers.py
lightningdata/thirdparty/torchmeta/datasets/helpers_tabular.py
lightningdata/thirdparty/torchmeta/datasets/letter.py
lightningdata/thirdparty/torchmeta/datasets/miniimagenet.py
lightningdata/thirdparty/torchmeta/datasets/omniglot.py
lightningdata/thirdparty/torchmeta/datasets/one_hundred_plants_margin.py
lightningdata/thirdparty/torchmeta/datasets/one_hundred_plants_shape.py
lightningdata/thirdparty/torchmeta/datasets/one_hundred_plants_texture.py
lightningdata/thirdparty/torchmeta/datasets/pascal5i.py
lightningdata_modules.egg-info/PKG-INFO
lightningdata_modules.egg-info/SOURCES.txt
lightningdata_modules.egg-info/dependency_links.txt
lightningdata_modules.egg-info/requires.txt
lightningdata_modules.egg-info/top_level.txt