Metadata-Version: 2.1
Name: lightningdata-modules
Version: 0.1.9
Summary: Pre-packages Pytorch-Lightning datasets
Home-page: https://github.com/ManuelRoeder/lightningdata-modules
Author: Manuel Roeder
Author-email: manuel.roeder@web.de
License: MIT
Platform: UNKNOWN
Classifier: Development Status :: 3 - Alpha
Classifier: Intended Audience :: Science/Research
Classifier: License :: OSI Approved :: MIT License
Classifier: Operating System :: OS Independent
Classifier: Programming Language :: Python :: 3.8
Classifier: Topic :: Scientific/Engineering :: Artificial Intelligence
Requires-Python: >=3.8.12
